p3k/P300Analysis.py
p3k/__init__.py
p3k/channels.py
p3k/epoching.py
p3k/params.py
p3k/plots.py
p3k/classification/__init__.py
p3k/classification/lda_epochwise.py
p3k/classification/lda_p3oddball.py
p3k/classification/rsquared.py
p3k/classification/utils.py
p3k/read/__init__.py
p3k/read/read_eeg.py
p3k/read/bci_format/__init__.py
p3k/read/bci_format/bci2000.py
p3k/read/bci_format/openvibe.py
p3k/signal_processing/ASR.py
p3k/signal_processing/__init__.py
p3k/signal_processing/artifact_rejection.py
p3k/signal_processing/rereference.py
p3k-0.1.9.dist-info/METADATA
p3k-0.1.9.dist-info/WHEEL
p3k-0.1.9.dist-info/top_level.txt
p3k-0.1.9.dist-info/RECORD
